PyProcTree/__init__.py
PyProcTree/add_naive_dependencies.py
PyProcTree/add_noise.py
PyProcTree/add_random_dependencies_tree.py
PyProcTree/case_attribute.py
PyProcTree/convert_to_ptml.py
PyProcTree/decision_table.py
PyProcTree/exposed_func.py
PyProcTree/generateTree.py
PyProcTree/generate_logs.py
PyProcTree/generate_newick_trees.py
PyProcTree/newick.py
PyProcTree/no_unique_traces.py
PyProcTree/simulateLog.py
PyProcTree/simulateTrace.py
PyProcTree/simulate_tree_with_rules.py
PyProcTree/timing.py
PyProcTree/tree.py
PyProcTree/tree_to_graphviz.py
PyProcTree/tree_with_data_dependencies.py
PyProcTree/utils.py
PyProcTree/xes_writer.py
PyProcTree/simpy/__init__.py
PyProcTree/simpy/_compat.py
PyProcTree/simpy/core.py
PyProcTree/simpy/events.py
PyProcTree/simpy/rt.py
PyProcTree/simpy/util.py
PyProcTree/simpy/resources/__init__.py
PyProcTree/simpy/resources/base.py
PyProcTree/simpy/resources/container.py
PyProcTree/simpy/resources/resource.py
PyProcTree/simpy/resources/store.py
PyProcTree-0.1.0.dist-info/LICENSE
PyProcTree-0.1.0.dist-info/METADATA
PyProcTree-0.1.0.dist-info/WHEEL
PyProcTree-0.1.0.dist-info/top_level.txt
PyProcTree-0.1.0.dist-info/RECORD
