Metadata-Version: 2.1
Name: PyProcTree
Version: 0.1.0
Summary: A Python package for process discovery using GNNs.
Home-page: https://github.com/jaxels20/PyProcTree
Author: Anonymous
Classifier: Programming Language :: Python :: 3
Classifier: License :: OSI Approved :: MIT License
Classifier: Operating System :: OS Independent
Requires-Python: >=3.12
License-File: LICENSE
